diskovery/__init__.py
diskovery/main.py
diskovery/stages/__init__.py
diskovery/stages/stage1_disk_imaging.py
diskovery/stages/stage2_extraction.py
diskovery/stages/stage3_categorization.py
diskovery/stages/stage4_2_keyword.py
diskovery/stages/stage4_filtering.py
diskovery/stages/stage5_reporting.py
diskovery/utils/__init__.py
diskovery/utils/run_command.py
diskovery-0.1.2.dist-info/licenses/LICENSE
diskovery-0.1.2.dist-info/METADATA
diskovery-0.1.2.dist-info/WHEEL
diskovery-0.1.2.dist-info/entry_points.txt
diskovery-0.1.2.dist-info/top_level.txt
diskovery-0.1.2.dist-info/RECORD
