Metadata-Version: 2.4
Name: diskovery
Version: 0.1.2
Summary: DISKOVERY: Disk Forensics Tool for Data Categorization & Keyword Filtering
Home-page: https://github.com/simmithapad/DISKOVERY
Author: Simmi Thapad, Vrinda Abrol
License: MIT
Classifier: Programming Language :: Python :: 3
Requires-Python: >=3.7
License-File: LICENSE
Requires-Dist: acres==0.3.0
Requires-Dist: certifi==2025.1.31
Requires-Dist: chardet==5.2.0
Requires-Dist: charset-normalizer==3.4.1
Requires-Dist: ci-info==0.3.0
Requires-Dist: click==8.1.8
Requires-Dist: configobj==5.0.9
Requires-Dist: configparser==7.2.0
Requires-Dist: contourpy==1.3.2
Requires-Dist: cycler==0.12.1
Requires-Dist: defusedxml==0.7.1
Requires-Dist: docx==0.2.4
Requires-Dist: docx2txt==0.9
Requires-Dist: etelemetry==0.3.1
Requires-Dist: filelock==3.18.0
Requires-Dist: fls==0.0.1.241224
Requires-Dist: fonttools==4.57.0
Requires-Dist: fpdf==1.7.2
Requires-Dist: httplib2==0.22.0
Requires-Dist: idna==3.10
Requires-Dist: isodate==0.6.1
Requires-Dist: kiwisolver==1.4.8
Requires-Dist: libewf-python==20240506
Requires-Dist: looseversion==1.3.0
Requires-Dist: lxml==5.3.2
Requires-Dist: matplotlib==3.10.1
Requires-Dist: networkx==3.4.2
Requires-Dist: nibabel==5.3.2
Requires-Dist: nipype==1.10.0
Requires-Dist: numpy==2.2.4
Requires-Dist: packaging==24.2
Requires-Dist: pandas==2.2.3
Requires-Dist: pathlib==1.0.1
Requires-Dist: pillow==11.1.0
Requires-Dist: prov==2.0.1
Requires-Dist: puremagic==1.28
Requires-Dist: pydot==3.0.4
Requires-Dist: PyMuPDF==1.25.5
Requires-Dist: pyparsing==3.2.3
Requires-Dist: python-dateutil==2.9.0.post0
Requires-Dist: python-docx==1.1.2
Requires-Dist: pytsk3==20250312
Requires-Dist: pytz==2025.2
Requires-Dist: pyxnat==1.6.3
Requires-Dist: rdflib==6.3.2
Requires-Dist: reportlab==4.3.1
Requires-Dist: requests==2.32.3
Requires-Dist: scipy==1.15.2
Requires-Dist: setuptools==79.0.0
Requires-Dist: simplejson==3.20.1
Requires-Dist: six==1.17.0
Requires-Dist: tqdm==4.67.1
Requires-Dist: traits==7.0.2
Requires-Dist: typing_extensions==4.13.1
Requires-Dist: tzdata==2025.2
Requires-Dist: urllib3==2.3.0
Dynamic: author
Dynamic: classifier
Dynamic: description
Dynamic: description-content-type
Dynamic: home-page
Dynamic: license
Dynamic: license-file
Dynamic: requires-dist
Dynamic: requires-python
Dynamic: summary
